SSHService/__init__.py
SSHService/__main__.py
SSHService/api.py
SSHService/api_test.py
SSHService/const.py
SSHService/service.py
pih_ssh-1.1.dist-info/METADATA
pih_ssh-1.1.dist-info/WHEEL
pih_ssh-1.1.dist-info/entry_points.txt
pih_ssh-1.1.dist-info/top_level.txt
pih_ssh-1.1.dist-info/RECORD
